jsonschema_converter/__init__.py
jsonschema_converter/class_writer.py
jsonschema_converter/const.py
jsonschema_converter/main_parser.py
jsonschema_converter/schema_parser.py
jsonschema_converter/utils.py
jsonschema_converter/version.py
jsonschema_converter/cli/__init__.py
jsonschema_converter/cli/jsonschema_convert.py
jsonschema_converter/models/__init__.py
jsonschema_converter/models/json_schema_model.py
jsonschema_converter/models/pydantic_schema_model.py
jsonschema_converter/types/__init__.py
jsonschema_converter/types/types.py
jsonschema_converter-0.1.13.dist-info/LICENSE
jsonschema_converter-0.1.13.dist-info/METADATA
jsonschema_converter-0.1.13.dist-info/WHEEL
jsonschema_converter-0.1.13.dist-info/entry_points.txt
jsonschema_converter-0.1.13.dist-info/top_level.txt
jsonschema_converter-0.1.13.dist-info/RECORD
