Metadata-Version: 2.1
Name: jsonschema_converter
Version: 0.1.13
Summary: A converter from JSONSchema to Pydantic classes
Author-email: Giorgio Ripani <g.ripani93@gmail.com>
Project-URL: repository, https://github.com/gripani/jsonschemaPydanticConverter
Classifier: Programming Language :: Python :: 3
Classifier: License :: OSI Approved :: MIT License
Classifier: Operating System :: OS Independent
Requires-Python: >=3.11
License-File: LICENSE
Requires-Dist: pydantic ==2.5.3
Requires-Dist: loguru ==0.7.1
